{"cameraMode":{"drawMode":0,"name":"Shaded","section":"Shading Mode"},"sceneLighting":true,"audioPlay":false,"sceneViewState":{"m_AlwaysRefresh":false,"showFog":true,"showSkybox":true,"showFlares":true,"showImageEffects":true,"showParticleSystems":true,"showVisualEffectGraphs":true,"m_FxEnabled":true},"in2DMode":false,"pivot":{"x":-2.725524425506592,"y":0.12805414199829102,"z":1.7967109680175782},"rotation":{"x":0.10097040981054306,"y":-0.8930925726890564,"z":0.2537499964237213,"w":0.3594915270805359},"size":5.684909820556641,"orthographic":false}